emailHelpers/__init__.py
emailHelpers-1.2.1.dist-info/LICENSE
emailHelpers-1.2.1.dist-info/METADATA
emailHelpers-1.2.1.dist-info/WHEEL
emailHelpers-1.2.1.dist-info/top_level.txt
emailHelpers-1.2.1.dist-info/RECORD
