Metadata-Version: 2.1
Name: emailHelpers
Version: 1.2.1
Summary: An easy way to integrate email into your projects.
Home-page: https://family-richards.github.io/emailHelpers/
Author: Kendell R.
Author-email: kidscodingplace@gmail.com
License: MIT
Project-URL: Tracker, https://github.com/family-richards/emailHelpers/issues?q=is%3Aissue+is%3Aopen+sort%3Aupdated-desc
Project-URL: Source, https://github.com/family-richards/emailHelpers/
Project-URL: CI, https://github.com/family-richards/emailHelpers/actions
Project-URL: SayThanks!, https://saythanks.io/to/kidscodingplace@gmail.com
Platform: UNKNOWN
Classifier: Topic :: Communications :: Email
Classifier: Natural Language :: English
Classifier: Operating System :: OS Independent
Classifier: Programming Language :: Python :: 3 :: Only
Classifier: Topic :: Software Development :: Libraries :: Python Modules
Classifier: Development Status :: 5 - Production/Stable
Classifier: License :: OSI Approved :: MIT License
Requires-Python: >=3.0
